beanmachine/__init__.py
beanmachine/graph.cpython-39-darwin.so
beanmachine/minibm.py
beanmachine/applications/__init__.py
beanmachine/applications/clara/__init__.py
beanmachine/applications/clara/nmc.py
beanmachine/applications/clara/nmc_df.py
beanmachine/applications/hme/__init__.py
beanmachine/applications/hme/abstract_linear_model.py
beanmachine/applications/hme/abstract_model.py
beanmachine/applications/hme/configs.py
beanmachine/applications/hme/interface.py
beanmachine/applications/hme/null_mixture_model.py
beanmachine/applications/hme/patsy_mixed.py
beanmachine/applications/hme/priors.py
beanmachine/ppl/__init__.py
beanmachine/ppl/conftest.py
beanmachine/ppl/compiler/__init__.py
beanmachine/ppl/compiler/ast_patterns.py
beanmachine/ppl/compiler/ast_tools.py
beanmachine/ppl/compiler/beanstalk_common.py
beanmachine/ppl/compiler/bm_graph_builder.py
beanmachine/ppl/compiler/bm_to_bmg.py
beanmachine/ppl/compiler/bmg_node_types.py
beanmachine/ppl/compiler/bmg_nodes.py
beanmachine/ppl/compiler/bmg_requirements.py
beanmachine/ppl/compiler/bmg_types.py
beanmachine/ppl/compiler/broadcaster.py
beanmachine/ppl/compiler/copy_and_replace.py
beanmachine/ppl/compiler/copy_transformer.py
beanmachine/ppl/compiler/devectorizer_transformer.py
beanmachine/ppl/compiler/error_report.py
beanmachine/ppl/compiler/execution_context.py
beanmachine/ppl/compiler/fix_additions.py
beanmachine/ppl/compiler/fix_arithmetic.py
beanmachine/ppl/compiler/fix_beta_conjugate_prior.py
beanmachine/ppl/compiler/fix_bool_arithmetic.py
beanmachine/ppl/compiler/fix_bool_comparisons.py
beanmachine/ppl/compiler/fix_logsumexp.py
beanmachine/ppl/compiler/fix_matrix_scale.py
beanmachine/ppl/compiler/fix_multiary_ops.py
beanmachine/ppl/compiler/fix_normal_conjugate_prior.py
beanmachine/ppl/compiler/fix_observations.py
beanmachine/ppl/compiler/fix_observe_true.py
beanmachine/ppl/compiler/fix_problem.py
beanmachine/ppl/compiler/fix_problems.py
beanmachine/ppl/compiler/fix_requirements.py
beanmachine-0.2.0.dist-info/LICENSE
beanmachine-0.2.0.dist-info/METADATA
beanmachine-0.2.0.dist-info/WHEEL
beanmachine-0.2.0.dist-info/top_level.txt
beanmachine-0.2.0.dist-info/RECORD
