Metadata-Version: 2.1
Name: beanmachine
Version: 0.2.0
Summary: Probabilistic Programming Language for Bayesian Inference
Home-page: https://beanmachine.org
Author: Meta Platforms, Inc.
License: MIT
Project-URL: Documentation, https://beanmachine.org
Project-URL: Source, https://github.com/facebookresearch/beanmachine
Keywords: Probabilistic Programming Language,Bayesian Inference,Statistical Modeling,MCMC,Variational Inference,PyTorch
Classifier: Development Status :: 3 - Alpha
Classifier: Programming Language :: Python :: 3 :: Only
Classifier: License :: OSI Approved :: MIT License
Classifier: Topic :: Scientific/Engineering
Classifier: Intended Audience :: Science/Research
Classifier: Intended Audience :: Developers
Requires-Python: >=3.7
Provides-Extra: dev
Provides-Extra: test
Provides-Extra: tutorials
License-File: LICENSE
